flytekitplugins_onnxtensorflow-1.16.12-py3.14-nspkg.pth
flytekitplugins/onnxtensorflow/__init__.py
flytekitplugins/onnxtensorflow/schema.py
flytekitplugins_onnxtensorflow-1.16.12.dist-info/METADATA
flytekitplugins_onnxtensorflow-1.16.12.dist-info/WHEEL
flytekitplugins_onnxtensorflow-1.16.12.dist-info/namespace_packages.txt
flytekitplugins_onnxtensorflow-1.16.12.dist-info/top_level.txt
flytekitplugins_onnxtensorflow-1.16.12.dist-info/RECORD
